[
    {
        "cardName": "Raging River",
        "cardSet": "2ed",
        "cardType": "Enchantment",
        "cardFront": "https://cards.scryfall.io/normal/front/7/e/7ee63877-056e-413d-932a-a393a4183686.jpg",
        "cardBack": ""
    },
    {
        "cardName": "Tornellan Protector",
        "cardSet": "psdg",
        "cardType": "Creature \u2014 Cleric",
        "cardFront": "https://cards.scryfall.io/normal/front/0/2/02c3ec3f-7b12-4aa7-ac01-3c1175c47228.jpg",
        "cardBack": ""
    },
    {
        "cardName": "Death Grasp",
        "cardSet": "c15",
        "cardType": "Sorcery",
        "cardFront": "https://cards.scryfall.io/normal/front/7/c/7cd6f616-2b22-42ed-818d-02d4a474ca8f.jpg",
        "cardBack": ""
    },
    {
        "cardName": "Zagras, Thief of Heartbeats",
        "cardSet": "znr",
        "cardType": "Legendary Creature \u2014 Vampire Rogue",
        "cardFront": "https://cards.scryfall.io/normal/front/a/c/ac81448c-f87b-4ca1-b951-b359216ab1d0.jpg",
        "cardBack": ""
    },
    {
        "cardName": "Key to the City",
        "cardSet": "c21",
        "cardType": "Artifact",
        "cardFront": "https://cards.scryfall.io/normal/front/f/2/f2103bba-f367-45ed-9b2c-bf31bb2926a5.jpg",
        "cardBack": ""
    },
    {
        "cardName": "Conversion",
        "cardSet": "me4",
        "cardType": "Enchantment",
        "cardFront": "https://cards.scryfall.io/normal/front/7/0/70bad071-f01e-4309-b37a-a3ea45dc7d3a.jpg",
        "cardBack": ""
    },
    {
        "cardName": "Blinking Spirit",
        "cardSet": "9ed",
        "cardType": "Creature \u2014 Spirit",
        "cardFront": "https://cards.scryfall.io/normal/front/6/9/692ac387-be1f-48e0-945e-cbb1254d395c.jpg",
        "cardBack": ""
    },
    {
        "cardName": "Shared Animosity",
        "cardSet": "lcc",
        "cardType": "Enchantment",
        "cardFront": "https://cards.scryfall.io/normal/front/1/b/1bd77ae9-c5ba-44af-80e9-7c852722ef6c.jpg",
        "cardBack": ""
    },
    {
        "cardName": "Arc-Slogger",
        "cardSet": "mrd",
        "cardType": "Creature \u2014 Beast",
        "cardFront": "https://cards.scryfall.io/normal/front/d/3/d3dd67e0-72b4-4c55-b49b-c69950feccb1.jpg",
        "cardBack": ""
    },
    {
        "cardName": "Helitrooper",
        "cardSet": "fic",
        "cardType": "Creature \u2014 Human Soldier",
        "cardFront": "https://cards.scryfall.io/normal/front/2/0/2073f387-9cdd-4184-8704-e6031c934b6d.jpg",
        "cardBack": ""
    },
    {
        "cardName": "Tempting Wurm",
        "cardSet": "ons",
        "cardType": "Creature \u2014 Wurm",
        "cardFront": "https://cards.scryfall.io/normal/front/8/5/857c2b6c-cfdf-4c88-a334-2937cb7db603.jpg",
        "cardBack": ""
    },
    {
        "cardName": "Labyrinth Raptor",
        "cardSet": "iko",
        "cardType": "Creature \u2014 Nightmare Dinosaur",
        "cardFront": "https://cards.scryfall.io/normal/front/c/6/c608543d-cb60-44c3-a437-e4a18c311420.jpg",
        "cardBack": ""
    },
    {
        "cardName": "Connecting the Dots",
        "cardSet": "mkm",
        "cardType": "Enchantment",
        "cardFront": "https://cards.scryfall.io/normal/front/8/e/8e02731a-8698-4b41-99c3-f0a19fc31430.jpg",
        "cardBack": ""
    },
    {
        "cardName": "Lothl\u00f3rien Blade",
        "cardSet": "ltc",
        "cardType": "Artifact \u2014 Equipment",
        "cardFront": "https://cards.scryfall.io/normal/front/3/f/3f7f1d3b-d6bb-4ddb-81d8-12f7aaaec49e.jpg",
        "cardBack": ""
    },
    {
        "cardName": "Darkslick Shores",
        "cardSet": "otc",
        "cardType": "Land",
        "cardFront": "https://cards.scryfall.io/normal/front/c/4/c49305d1-ac95-43ea-b02d-c3c7205bcda6.jpg",
        "cardBack": ""
    },
    {
        "cardName": "\"Ach! Hans, Run!\"",
        "cardSet": "unh",
        "cardType": "Enchantment",
        "cardFront": "https://cards.scryfall.io/normal/front/8/4/84f2c8f5-8e11-4639-b7de-00e4a2cbabee.jpg",
        "cardBack": ""
    },
    {
        "cardName": "Ramunap Hydra",
        "cardSet": "hou",
        "cardType": "Creature \u2014 Snake Hydra",
        "cardFront": "https://cards.scryfall.io/normal/front/9/5/953f3722-2126-4eb3-a3d8-cff4b0703a9c.jpg",
        "cardBack": ""
    },
    {
        "cardName": "Planeswalkerificate",
        "cardSet": "mb2",
        "cardType": "Enchantment \u2014 Aura",
        "cardFront": "https://cards.scryfall.io/normal/front/f/e/fef4c08c-447e-4a15-859f-45927c06984f.jpg",
        "cardBack": ""
    },
    {
        "cardName": "Mana Clash",
        "cardSet": "9ed",
        "cardType": "Sorcery",
        "cardFront": "https://cards.scryfall.io/normal/front/b/d/bd41352f-617f-40f6-b612-11022180c18b.jpg",
        "cardBack": ""
    },
    {
        "cardName": "Murderous Betrayal",
        "cardSet": "8ed",
        "cardType": "Enchantment",
        "cardFront": "https://cards.scryfall.io/normal/front/0/0/0063ed19-494b-4199-9120-d479bfcb625a.jpg",
        "cardBack": ""
    },
    {
        "cardName": "Keeper of Progenitus",
        "cardSet": "ala",
        "cardType": "Creature \u2014 Elf Druid",
        "cardFront": "https://cards.scryfall.io/normal/front/b/c/bcb023a2-e929-47e9-bd58-cbc6f241e7a4.jpg",
        "cardBack": ""
    },
    {
        "cardName": "Cramped Bunker",
        "cardSet": "ust",
        "cardType": "Enchantment",
        "cardFront": "https://cards.scryfall.io/normal/front/a/a/aa775e1e-2322-4981-bf14-4f24a3be983e.jpg",
        "cardBack": ""
    },
    {
        "cardName": "Crack in Time",
        "cardSet": "who",
        "cardType": "Enchantment",
        "cardFront": "https://cards.scryfall.io/normal/front/5/5/559e77be-42a2-47cf-a2cf-057b37384cb4.jpg",
        "cardBack": ""
    },
    {
        "cardName": "Confirm Suspicions",
        "cardSet": "mkc",
        "cardType": "Instant",
        "cardFront": "https://cards.scryfall.io/normal/front/1/d/1d1463af-8f22-4771-af19-3799ffe706b8.jpg",
        "cardBack": ""
    },
    {
        "cardName": "Spitting Image",
        "cardSet": "c21",
        "cardType": "Sorcery",
        "cardFront": "https://cards.scryfall.io/normal/front/d/5/d5f68c73-4794-4659-b494-edf89105beab.jpg",
        "cardBack": ""
    },
    {
        "cardName": "Zareth San, the Trickster",
        "cardSet": "znr",
        "cardType": "Legendary Creature \u2014 Merfolk Rogue",
        "cardFront": "https://cards.scryfall.io/normal/front/9/c/9cfe4fbe-277f-410c-9eee-f7617f4cb850.jpg",
        "cardBack": ""
    },
    {
        "cardName": "Dragon Turtle",
        "cardSet": "afr",
        "cardType": "Creature \u2014 Dragon Turtle",
        "cardFront": "https://cards.scryfall.io/normal/front/d/4/d436ba80-386f-40ad-b0ca-a98cc50de964.jpg",
        "cardBack": ""
    },
    {
        "cardName": "Kamahl's Will",
        "cardSet": "cmr",
        "cardType": "Instant",
        "cardFront": "https://cards.scryfall.io/normal/front/5/1/51fe007f-fddf-4b3a-b336-0a88df95cb14.jpg",
        "cardBack": ""
    },
    {
        "cardName": "Vanquish the Horde",
        "cardSet": "tdc",
        "cardType": "Sorcery",
        "cardFront": "https://cards.scryfall.io/normal/front/a/c/ac6ba8a3-5f6e-4eab-af91-fd58f7ea2028.jpg",
        "cardBack": ""
    },
    {
        "cardName": "Tendershoot Dryad",
        "cardSet": "rix",
        "cardType": "Creature \u2014 Dryad",
        "cardFront": "https://cards.scryfall.io/normal/front/a/1/a159830a-698f-423c-9da0-a734b210ecab.jpg",
        "cardBack": ""
    },
    {
        "cardName": "Leonin Arbiter",
        "cardSet": "2x2",
        "cardType": "Creature \u2014 Cat Cleric",
        "cardFront": "https://cards.scryfall.io/normal/front/0/d/0d0f827b-ebc3-45a4-8d12-c71a14478038.jpg",
        "cardBack": ""
    },
    {
        "cardName": "Morinfen Avatar",
        "cardSet": "pmoa",
        "cardType": "Vanguard",
        "cardFront": "https://cards.scryfall.io/normal/front/7/2/729f36b0-d389-4b54-a36f-f97b3b5f8034.jpg",
        "cardBack": ""
    },
    {
        "cardName": "Cloudsteel Kirin",
        "cardSet": "neo",
        "cardType": "Artifact Creature \u2014 Equipment Kirin",
        "cardFront": "https://cards.scryfall.io/normal/front/a/1/a13ddda7-da6e-415e-8886-295514f862d4.jpg",
        "cardBack": ""
    },
    {
        "cardName": "Djinn of Wishes",
        "cardSet": "c18",
        "cardType": "Creature \u2014 Djinn",
        "cardFront": "https://cards.scryfall.io/normal/front/a/5/a5491962-ad47-4919-b59c-510408bed29e.jpg",
        "cardBack": ""
    },
    {
        "cardName": "Scion of Vitu-Ghazi",
        "cardSet": "dgm",
        "cardType": "Creature \u2014 Elemental",
        "cardFront": "https://cards.scryfall.io/normal/front/3/c/3cd20865-0a9a-4a72-92f9-77c8d6384b46.jpg",
        "cardBack": ""
    },
    {
        "cardName": "Lost in the Woods",
        "cardSet": "dka",
        "cardType": "Enchantment",
        "cardFront": "https://cards.scryfall.io/normal/front/5/8/5865603c-0a5e-45c3-84e3-2dc3b4cf0cf7.jpg",
        "cardBack": ""
    },
    {
        "cardName": "Heroes",
        "cardSet": "fj25",
        "cardType": "Card",
        "cardFront": "https://cards.scryfall.io/normal/front/3/1/310f8ce9-0f17-4f56-b07f-c74b76e59518.jpg",
        "cardBack": ""
    },
    {
        "cardName": "Konda's Banner",
        "cardSet": "chk",
        "cardType": "Legendary Artifact \u2014 Equipment",
        "cardFront": "https://cards.scryfall.io/normal/front/7/5/759b2f39-e1b1-44aa-b49a-00ef6926a6ac.jpg",
        "cardBack": ""
    },
    {
        "cardName": "Roar of Endless Song",
        "cardSet": "tdm",
        "cardType": "Enchantment \u2014 Saga",
        "cardFront": "https://cards.scryfall.io/normal/front/7/a/7a9c3531-61a8-43f5-82a2-5166e5f5a6b9.jpg",
        "cardBack": ""
    },
    {
        "cardName": "Adult Gold Dragon",
        "cardSet": "afr",
        "cardType": "Creature \u2014 Dragon",
        "cardFront": "https://cards.scryfall.io/normal/front/6/7/67a76010-d932-4727-8b5e-b8e2d14e1362.jpg",
        "cardBack": ""
    },
    {
        "cardName": "Land Equilibrium",
        "cardSet": "me3",
        "cardType": "Enchantment",
        "cardFront": "https://cards.scryfall.io/normal/front/5/1/51c5df75-746c-4e4b-84f1-76b689d317d7.jpg",
        "cardBack": ""
    },
    {
        "cardName": "Synthesizer Labship",
        "cardSet": "eoe",
        "cardType": "Artifact \u2014 Spacecraft",
        "cardFront": "https://cards.scryfall.io/normal/front/f/b/fba6332c-acba-43f9-877c-ca6c5328aae9.jpg",
        "cardBack": ""
    },
    {
        "cardName": "Grenzo, Dungeon Warden",
        "cardSet": "a25",
        "cardType": "Legendary Creature \u2014 Goblin Rogue",
        "cardFront": "https://cards.scryfall.io/normal/front/6/e/6e19c383-88bd-4bde-ac81-c0eb6d5b5bd4.jpg",
        "cardBack": ""
    },
    {
        "cardName": "S\u00e9ance",
        "cardSet": "mm3",
        "cardType": "Enchantment",
        "cardFront": "https://cards.scryfall.io/normal/front/2/e/2e376bdf-076c-471a-9408-b36fc5b8405b.jpg",
        "cardBack": ""
    },
    {
        "cardName": "Ratonhnhak\u00e9\ua789ton",
        "cardSet": "acr",
        "cardType": "Legendary Creature \u2014 Human Assassin",
        "cardFront": "https://cards.scryfall.io/normal/front/2/b/2b16a212-602c-4839-9e34-fc5c5b0388f0.jpg",
        "cardBack": ""
    },
    {
        "cardName": "White Sun's Twilight",
        "cardSet": "one",
        "cardType": "Sorcery",
        "cardFront": "https://cards.scryfall.io/normal/front/f/f/fff13d77-8133-4328-b91e-efce229bc331.jpg",
        "cardBack": ""
    },
    {
        "cardName": "Floodwater Dam",
        "cardSet": "me4",
        "cardType": "Artifact",
        "cardFront": "https://cards.scryfall.io/normal/front/0/f/0f1bc264-1f28-4bd4-be23-baae9734c3d9.jpg",
        "cardBack": ""
    },
    {
        "cardName": "Fear of Sleep Paralysis",
        "cardSet": "dsc",
        "cardType": "Enchantment Creature \u2014 Nightmare",
        "cardFront": "https://cards.scryfall.io/normal/front/8/4/845e9d68-11a9-4759-a031-13464d337e12.jpg",
        "cardBack": ""
    },
    {
        "cardName": "Talent of the Telepath",
        "cardSet": "ori",
        "cardType": "Sorcery",
        "cardFront": "https://cards.scryfall.io/normal/front/c/5/c5da13a1-8be2-4312-a660-f3e102c552b6.jpg",
        "cardBack": ""
    },
    {
        "cardName": "Concealing Curtains // Revealing Eye",
        "cardSet": "vow",
        "cardType": "Creature \u2014 Wall // Creature \u2014 Eye Horror",
        "cardFront": "https://cards.scryfall.io/normal/front/6/1/612b2e6e-fe8d-49ad-b845-6fa7fa59ffd1.jpg",
        "cardBack": "https://cards.scryfall.io/normal/back/6/1/612b2e6e-fe8d-49ad-b845-6fa7fa59ffd1.jpg"
    }
]