[
    {
        "cardName": "Permafrost Trap",
        "cardSet": "wwk",
        "cardType": "Instant \u2014 Trap",
        "cardFront": "https://cards.scryfall.io/normal/front/0/3/03b6dc43-62d3-4572-a2e1-b0e67dcc21c7.jpg",
        "cardBack": ""
    },
    {
        "cardName": "The Binding of the Titans",
        "cardSet": "cmm",
        "cardType": "Enchantment \u2014 Saga",
        "cardFront": "https://cards.scryfall.io/normal/front/2/2/22c03969-db08-4af3-8c83-b13750e8b20a.jpg",
        "cardBack": ""
    },
    {
        "cardName": "Reprieve",
        "cardSet": "ltr",
        "cardType": "Instant",
        "cardFront": "https://cards.scryfall.io/normal/front/1/b/1bd3fa8a-6c50-4f7f-9ae3-0810eec5e3db.jpg",
        "cardBack": ""
    },
    {
        "cardName": "Earth Rumble",
        "cardSet": "tla",
        "cardType": "Sorcery",
        "cardFront": "https://cards.scryfall.io/normal/front/6/2/62730505-56f1-4043-a8b9-4fb7bc508b47.jpg",
        "cardBack": ""
    },
    {
        "cardName": "Fearless Skald",
        "cardSet": "mom",
        "cardType": "Creature \u2014 Dwarf Berserker",
        "cardFront": "https://cards.scryfall.io/normal/front/4/e/4e317d1d-3f20-4f0d-8b1e-31df351e8f83.jpg",
        "cardBack": ""
    },
    {
        "cardName": "Paragon of New Dawns",
        "cardSet": "m15",
        "cardType": "Creature \u2014 Human Soldier",
        "cardFront": "https://cards.scryfall.io/normal/front/3/6/361c66c3-b4eb-48aa-a967-255a8db60977.jpg",
        "cardBack": ""
    },
    {
        "cardName": "Bladewing's Thrall",
        "cardSet": "ima",
        "cardType": "Creature \u2014 Zombie",
        "cardFront": "https://cards.scryfall.io/normal/front/9/d/9d63d3d8-5699-4577-a908-4415bc96b404.jpg",
        "cardBack": ""
    },
    {
        "cardName": "Hymn of Rebirth",
        "cardSet": "me1",
        "cardType": "Sorcery",
        "cardFront": "https://cards.scryfall.io/normal/front/b/e/be69ba4b-934f-4ee8-849a-0df5a61ee804.jpg",
        "cardBack": ""
    },
    {
        "cardName": "Ribbons of Night",
        "cardSet": "clu",
        "cardType": "Sorcery",
        "cardFront": "https://cards.scryfall.io/normal/front/0/1/010eba83-30ec-4cca-b07e-f24d8d2f0787.jpg",
        "cardBack": ""
    },
    {
        "cardName": "Fiery Temper",
        "cardSet": "inr",
        "cardType": "Instant",
        "cardFront": "https://cards.scryfall.io/normal/front/1/d/1d3a3a1d-c393-4a57-8a0e-5907d1722331.jpg",
        "cardBack": ""
    },
    {
        "cardName": "Tawnos's Weaponry",
        "cardSet": "me4",
        "cardType": "Artifact",
        "cardFront": "https://cards.scryfall.io/normal/front/b/7/b73fe4b5-142f-4b1f-b48d-7aa65782bdb5.jpg",
        "cardBack": ""
    },
    {
        "cardName": "Seal of Removal",
        "cardSet": "mh2",
        "cardType": "Enchantment",
        "cardFront": "https://cards.scryfall.io/normal/front/6/d/6dfc7060-e374-486f-8029-d3fdfe4b61e7.jpg",
        "cardBack": ""
    },
    {
        "cardName": "Planar Chaos",
        "cardSet": "jud",
        "cardType": "Enchantment",
        "cardFront": "https://cards.scryfall.io/normal/front/5/d/5dae5e16-d2fc-488c-9c53-d35c377d6a00.jpg",
        "cardBack": ""
    },
    {
        "cardName": "Curse Artifact",
        "cardSet": "drk",
        "cardType": "Enchantment \u2014 Aura",
        "cardFront": "https://cards.scryfall.io/normal/front/9/f/9fc0d070-8a42-4d5e-8f2b-ceb59147de6f.jpg",
        "cardBack": ""
    },
    {
        "cardName": "Khenra Spellspear // Gitaxian Spellstalker",
        "cardSet": "mom",
        "cardType": "Creature \u2014 Jackal Warrior // Creature \u2014 Phyrexian Jackal",
        "cardFront": "https://cards.scryfall.io/normal/front/d/c/dc1454ce-bb49-4b4f-bbca-d77387fa4966.jpg",
        "cardBack": "https://cards.scryfall.io/normal/back/d/c/dc1454ce-bb49-4b4f-bbca-d77387fa4966.jpg"
    },
    {
        "cardName": "Brood Weaver",
        "cardSet": "mid",
        "cardType": "Creature \u2014 Spider",
        "cardFront": "https://cards.scryfall.io/normal/front/e/2/e24e2f49-70f9-445f-af03-2ef43798004a.jpg",
        "cardBack": ""
    },
    {
        "cardName": "Sanguimancy",
        "cardSet": "bng",
        "cardType": "Sorcery",
        "cardFront": "https://cards.scryfall.io/normal/front/f/b/fb129def-4055-4b12-9944-39406b451553.jpg",
        "cardBack": ""
    },
    {
        "cardName": "Boa Constrictor",
        "cardSet": "mmq",
        "cardType": "Creature \u2014 Snake",
        "cardFront": "https://cards.scryfall.io/normal/front/f/7/f7369cbf-6986-4a39-b07c-a283b40aee40.jpg",
        "cardBack": ""
    },
    {
        "cardName": "Golgari Charm",
        "cardSet": "uma",
        "cardType": "Instant",
        "cardFront": "https://cards.scryfall.io/normal/front/9/d/9d467e61-bbec-4cea-bd5d-f10555910c9d.jpg",
        "cardBack": ""
    },
    {
        "cardName": "Graverobber Spider",
        "cardSet": "bng",
        "cardType": "Creature \u2014 Spider",
        "cardFront": "https://cards.scryfall.io/normal/front/4/1/41810472-ba24-44b6-886c-f8906ff0a7df.jpg",
        "cardBack": ""
    },
    {
        "cardName": "Strength of the Coalition",
        "cardSet": "dmu",
        "cardType": "Instant",
        "cardFront": "https://cards.scryfall.io/normal/front/8/4/8418c504-24fe-470f-8102-dcad68ba1520.jpg",
        "cardBack": ""
    },
    {
        "cardName": "Muster the Departed",
        "cardSet": "mh3",
        "cardType": "Enchantment",
        "cardFront": "https://cards.scryfall.io/normal/front/a/3/a37510bb-245c-47bc-bbf3-2b202b67d383.jpg",
        "cardBack": ""
    },
    {
        "cardName": "Rush of Blood",
        "cardSet": "avr",
        "cardType": "Instant",
        "cardFront": "https://cards.scryfall.io/normal/front/a/2/a2884824-d138-47f2-913b-32cd475e9584.jpg",
        "cardBack": ""
    },
    {
        "cardName": "Perception Bobblehead",
        "cardSet": "pip",
        "cardType": "Artifact \u2014 Bobblehead",
        "cardFront": "https://cards.scryfall.io/normal/front/e/2/e2a8c89c-2cd1-4f68-9758-449177be2880.jpg",
        "cardBack": ""
    },
    {
        "cardName": "Lantern of the Lost",
        "cardSet": "vow",
        "cardType": "Artifact",
        "cardFront": "https://cards.scryfall.io/normal/front/c/2/c2303f11-2c82-44d5-893a-8e71dece7746.jpg",
        "cardBack": ""
    },
    {
        "cardName": "Waylay",
        "cardSet": "usg",
        "cardType": "Instant",
        "cardFront": "https://cards.scryfall.io/normal/front/8/6/867a33ee-0340-413a-8243-9d6bc2d944e2.jpg",
        "cardBack": ""
    },
    {
        "cardName": "Murderer's Axe",
        "cardSet": "soi",
        "cardType": "Artifact \u2014 Equipment",
        "cardFront": "https://cards.scryfall.io/normal/front/6/9/696dcb79-4915-424f-ba8f-5363ae3395a6.jpg",
        "cardBack": ""
    },
    {
        "cardName": "Cleric Class",
        "cardSet": "afr",
        "cardType": "Enchantment \u2014 Class",
        "cardFront": "https://cards.scryfall.io/normal/front/4/7/47ce8b7e-d8e1-489a-a69e-99089eeb8739.jpg",
        "cardBack": ""
    },
    {
        "cardName": "Karplusan Giant",
        "cardSet": "me2",
        "cardType": "Creature \u2014 Giant",
        "cardFront": "https://cards.scryfall.io/normal/front/6/7/67c031e0-7f5c-4c12-884b-d30eed5e888b.jpg",
        "cardBack": ""
    },
    {
        "cardName": "Attack-in-the-Box",
        "cardSet": "dsk",
        "cardType": "Artifact Creature \u2014 Toy",
        "cardFront": "https://cards.scryfall.io/normal/front/a/4/a477dc3e-0fa1-4ce4-b3de-8cae0d1a0763.jpg",
        "cardBack": ""
    },
    {
        "cardName": "Trash Bin",
        "cardSet": "unf",
        "cardType": "Artifact \u2014 Attraction",
        "cardFront": "https://cards.scryfall.io/normal/front/f/0/f07c39f7-5c3e-40f6-b584-458b65282a7e.jpg",
        "cardBack": ""
    },
    {
        "cardName": "Leeching Sliver",
        "cardSet": "m15",
        "cardType": "Creature \u2014 Sliver",
        "cardFront": "https://cards.scryfall.io/normal/front/8/8/888ca52b-1270-4587-804d-1d08b07d7c5d.jpg",
        "cardBack": ""
    },
    {
        "cardName": "Corrupted Harvester",
        "cardSet": "som",
        "cardType": "Creature \u2014 Phyrexian Horror",
        "cardFront": "https://cards.scryfall.io/normal/front/b/5/b54625ac-484f-4522-8048-38e01c545ac3.jpg",
        "cardBack": ""
    },
    {
        "cardName": "Fanatic of Xenagos",
        "cardSet": "bng",
        "cardType": "Creature \u2014 Centaur Warrior",
        "cardFront": "https://cards.scryfall.io/normal/front/3/6/3687799c-81bd-4c49-902a-2a96863629c3.jpg",
        "cardBack": ""
    },
    {
        "cardName": "Clandestine Meddler",
        "cardSet": "mkm",
        "cardType": "Creature \u2014 Vampire Rogue",
        "cardFront": "https://cards.scryfall.io/normal/front/2/e/2e069de0-3218-456c-b191-93e755634783.jpg",
        "cardBack": ""
    },
    {
        "cardName": "Kami of Whispered Hopes",
        "cardSet": "mom",
        "cardType": "Creature \u2014 Spirit",
        "cardFront": "https://cards.scryfall.io/normal/front/5/c/5c644650-3861-4a78-9e39-a413b073ddac.jpg",
        "cardBack": ""
    },
    {
        "cardName": "Fanatical Fever",
        "cardSet": "ice",
        "cardType": "Instant",
        "cardFront": "https://cards.scryfall.io/normal/front/2/a/2abba7f1-5d07-4137-88a2-5967396a3e42.jpg",
        "cardBack": ""
    },
    {
        "cardName": "Howling Galefang",
        "cardSet": "woe",
        "cardType": "Creature \u2014 Beast",
        "cardFront": "https://cards.scryfall.io/normal/front/8/6/86311523-d0eb-4db3-b586-8349de9c2d37.jpg",
        "cardBack": ""
    },
    {
        "cardName": "Dagger Caster",
        "cardSet": "clu",
        "cardType": "Creature \u2014 Lizard Rogue",
        "cardFront": "https://cards.scryfall.io/normal/front/f/d/fde4b3c2-00fd-4911-a52c-9c8247287cfd.jpg",
        "cardBack": ""
    },
    {
        "cardName": "Emrakul's Messenger",
        "cardSet": "mh3",
        "cardType": "Creature \u2014 Eldrazi Faerie Rogue",
        "cardFront": "https://cards.scryfall.io/normal/front/f/0/f0f818d7-320c-47b9-a083-40007f3d91ea.jpg",
        "cardBack": ""
    },
    {
        "cardName": "Landslide",
        "cardSet": "uds",
        "cardType": "Sorcery",
        "cardFront": "https://cards.scryfall.io/normal/front/c/0/c0ddc0dc-8783-4659-bbbd-db6698843b47.jpg",
        "cardBack": ""
    },
    {
        "cardName": "Unseen Walker",
        "cardSet": "6ed",
        "cardType": "Creature \u2014 Dryad",
        "cardFront": "https://cards.scryfall.io/normal/front/b/c/bc03eea5-ff21-4f4d-b4c2-ce9d8f456440.jpg",
        "cardBack": ""
    },
    {
        "cardName": "Sunpearl Kirin",
        "cardSet": "tdm",
        "cardType": "Creature \u2014 Kirin",
        "cardFront": "https://cards.scryfall.io/normal/front/1/8/18292b9c-0f42-4ce2-8b85-35d06cf45a63.jpg",
        "cardBack": ""
    },
    {
        "cardName": "Haze of Rage",
        "cardSet": "tsr",
        "cardType": "Sorcery",
        "cardFront": "https://cards.scryfall.io/normal/front/c/3/c344b885-68c6-43d2-b6c1-6c89b3c94983.jpg",
        "cardBack": ""
    },
    {
        "cardName": "Liberate",
        "cardSet": "inv",
        "cardType": "Instant",
        "cardFront": "https://cards.scryfall.io/normal/front/9/6/96794470-31ea-478f-b11c-dc8342a508e2.jpg",
        "cardBack": ""
    },
    {
        "cardName": "Scour",
        "cardSet": "bok",
        "cardType": "Instant",
        "cardFront": "https://cards.scryfall.io/normal/front/a/9/a9cac762-7482-471f-b4de-e0cb6da5451c.jpg",
        "cardBack": ""
    },
    {
        "cardName": "Angel's Trumpet",
        "cardSet": "ulg",
        "cardType": "Artifact",
        "cardFront": "https://cards.scryfall.io/normal/front/0/c/0c7b248a-3c74-4592-b357-47989568298c.jpg",
        "cardBack": ""
    },
    {
        "cardName": "Road // Ruin",
        "cardSet": "mh2",
        "cardType": "Instant // Sorcery",
        "cardFront": "https://cards.scryfall.io/normal/front/f/3/f336b4d4-9a84-4a87-a8ea-a83a842890ee.jpg",
        "cardBack": ""
    },
    {
        "cardName": "Long River's Pull",
        "cardSet": "blb",
        "cardType": "Instant",
        "cardFront": "https://cards.scryfall.io/normal/front/1/c/1c81d0fa-81a1-4f9b-a5fd-5a648fd01dea.jpg",
        "cardBack": ""
    },
    {
        "cardName": "Lava-Field Overlord",
        "cardSet": "bbd",
        "cardType": "Creature \u2014 Dragon",
        "cardFront": "https://cards.scryfall.io/normal/front/8/4/8465c5dd-c246-49e4-89bf-18e022816162.jpg",
        "cardBack": ""
    }
]